scripbox/__init__.py
scripbox/api.py
scripbox/auth.py
scripbox/cli.py
scripbox/token_manager.py
scripbox-0.1.1.dist-info/METADATA
scripbox-0.1.1.dist-info/WHEEL
scripbox-0.1.1.dist-info/entry_points.txt
scripbox-0.1.1.dist-info/top_level.txt
scripbox-0.1.1.dist-info/RECORD
