Metadata-Version: 2.4
Name: scripbox
Version: 0.1.1
Summary: A CLI tool for logging into Scripbox
Home-page: https://github.com/YBR1104/scripbox
Author: YASHWANTH BR
Classifier: Programming Language :: Python :: 3
Classifier: License :: OSI Approved :: MIT License
Classifier: Operating System :: OS Independent
Requires-Python: >=3.6
Requires-Dist: requests
Dynamic: author
Dynamic: classifier
Dynamic: description
Dynamic: description-content-type
Dynamic: home-page
Dynamic: requires-dist
Dynamic: requires-python
Dynamic: summary
